django_elb_health_check_middleware/__init__.py
django_elb_health_check_middleware/asgi.py
django_elb_health_check_middleware/settings.py
django_elb_health_check_middleware/urls.py
django_elb_health_check_middleware/wsgi.py
elb_health_check/__init__.py
elb_health_check/admin.py
elb_health_check/apps.py
elb_health_check/middleware.py
elb_health_check/models.py
elb_health_check/tests.py
elb_health_check/views.py
elb_health_check/migrations/__init__.py
django_elb_health_check_middleware-0.1.0.dist-info/LICENSE
django_elb_health_check_middleware-0.1.0.dist-info/METADATA
django_elb_health_check_middleware-0.1.0.dist-info/WHEEL
django_elb_health_check_middleware-0.1.0.dist-info/top_level.txt
django_elb_health_check_middleware-0.1.0.dist-info/RECORD
