Metadata-Version: 2.1
Name: django-elb-health-check-middleware
Version: 0.1.0
Summary: Process ELB health checks efficiently, no crazy IP lookups.
Home-page: https://github.com/BillSchumacher/django-elb-health-check-middleware
Author: Bill Schumacher
Author-email: william.schumacher@gmail.com
License: MIT
Classifier: License :: OSI Approved :: MIT License
Classifier: Framework :: Django
Classifier: Framework :: Django :: 4.0
Classifier: Programming Language :: Python
Classifier: Programming Language :: Python :: 3.10
Classifier: Programming Language :: Python :: 3.9
Classifier: Programming Language :: Python :: 3.8
Classifier: Topic :: Software Development :: Libraries
License-File: LICENSE
Requires-Dist: django
